odoo/addons/realestate_estate/README.rst
odoo/addons/realestate_estate/__init__.py
odoo/addons/realestate_estate/__manifest__.py
odoo/addons/realestate_estate/data/ir_sequence.xml
odoo/addons/realestate_estate/data/real_estate_type.xml
odoo/addons/realestate_estate/demo/real_estate.xml
odoo/addons/realestate_estate/i18n/fr_BE.po
odoo/addons/realestate_estate/i18n/realestate_estate.pot
odoo/addons/realestate_estate/models/__init__.py
odoo/addons/realestate_estate/models/real_estate.py
odoo/addons/realestate_estate/models/real_estate_type.py
odoo/addons/realestate_estate/models/res_partner.py
odoo/addons/realestate_estate/readme/CONTRIBUTORS.rst
odoo/addons/realestate_estate/readme/DESCRIPTION.rst
odoo/addons/realestate_estate/security/real_estate.xml
odoo/addons/realestate_estate/security/real_estate_type.xml
odoo/addons/realestate_estate/static/description/icon.png
odoo/addons/realestate_estate/static/description/index.html
odoo/addons/realestate_estate/views/real_estate.xml
odoo/addons/realestate_estate/views/real_estate_type.xml
odoo13_addon_realestate_estate-13.0.1.0.1.dist-info/METADATA
odoo13_addon_realestate_estate-13.0.1.0.1.dist-info/WHEEL
odoo13_addon_realestate_estate-13.0.1.0.1.dist-info/top_level.txt
odoo13_addon_realestate_estate-13.0.1.0.1.dist-info/RECORD
